{"errors":[],"warnings":[],"namedChunkGroups":{"app":{"chunks":[7,2],"assets":["webpack-runtime-e4ae3b467134826e3710.js","webpack-runtime-e4ae3b467134826e3710.js.map","app-d9fef0408d160dfb28e1.js","app-d9fef0408d160dfb28e1.js.map"],"children":{},"childAssets":{}},"component---src-pages-404-js":{"chunks":[0,1,3],"assets":["styles.4f66268be0d4644ad4ac.css","styles-500c8aa74ac3eb786e65.js","styles-500c8aa74ac3eb786e65.js.map","1-2cc0f47f131771f02d58.js","1-2cc0f47f131771f02d58.js.map","component---src-pages-404-js-1bcce646025be4f95eb6.js","component---src-pages-404-js-1bcce646025be4f95eb6.js.map"],"children":{},"childAssets":{}},"component---src-pages-index-js":{"chunks":[0,1,4],"assets":["styles.4f66268be0d4644ad4ac.css","styles-500c8aa74ac3eb786e65.js","styles-500c8aa74ac3eb786e65.js.map","1-2cc0f47f131771f02d58.js","1-2cc0f47f131771f02d58.js.map","component---src-pages-index-js-35bee9af94b82ddbbb20.js","component---src-pages-index-js-35bee9af94b82ddbbb20.js.map"],"children":{},"childAssets":{}},"component---src-pages-page-2-js":{"chunks":[0,1,5],"assets":["styles.4f66268be0d4644ad4ac.css","styles-500c8aa74ac3eb786e65.js","styles-500c8aa74ac3eb786e65.js.map","1-2cc0f47f131771f02d58.js","1-2cc0f47f131771f02d58.js.map","component---src-pages-page-2-js-668cdc74e096dcfcab4f.js","component---src-pages-page-2-js-668cdc74e096dcfcab4f.js.map"],"children":{},"childAssets":{}},"pages-manifest":{"chunks":[6],"assets":["pages-manifest-b0843e4b4c8b7a32ee65.js","pages-manifest-b0843e4b4c8b7a32ee65.js.map"],"children":{},"childAssets":{}}},"assetsByChunkName":{"app":["webpack-runtime-e4ae3b467134826e3710.js","app-d9fef0408d160dfb28e1.js"],"component---src-pages-404-js":["styles.4f66268be0d4644ad4ac.css","styles-500c8aa74ac3eb786e65.js","1-2cc0f47f131771f02d58.js","component---src-pages-404-js-1bcce646025be4f95eb6.js"],"component---src-pages-index-js":["styles.4f66268be0d4644ad4ac.css","styles-500c8aa74ac3eb786e65.js","1-2cc0f47f131771f02d58.js","component---src-pages-index-js-35bee9af94b82ddbbb20.js"],"component---src-pages-page-2-js":["styles.4f66268be0d4644ad4ac.css","styles-500c8aa74ac3eb786e65.js","1-2cc0f47f131771f02d58.js","component---src-pages-page-2-js-668cdc74e096dcfcab4f.js"],"pages-manifest":["pages-manifest-b0843e4b4c8b7a32ee65.js"]}}